ratelimit_anyio/__init__.py
ratelimit_anyio-0.2.0.dist-info/LICENSE.txt
ratelimit_anyio-0.2.0.dist-info/METADATA
ratelimit_anyio-0.2.0.dist-info/WHEEL
ratelimit_anyio-0.2.0.dist-info/RECORD
