Metadata-Version: 2.1
Name: ratelimit-anyio
Version: 0.2.0
Summary: Rate limit decorator
Home-page: https://github.com/rafalkrupinski/ratelimit-anyio.git
License: Apache-2.0
Author: Rafal Krupinski
Author-email: 10319569-mattesilver@users.noreply.gitlab.com
Requires-Python: >=3.8,<4.0
Classifier: Development Status :: 3 - Alpha
Classifier: Intended Audience :: Developers
Classifier: License :: OSI Approved :: Apache Software License
Classifier: Programming Language :: Python :: 3
Classifier: Programming Language :: Python :: 3.8
Classifier: Programming Language :: Python :: 3.9
Classifier: Programming Language :: Python :: 3.10
Classifier: Programming Language :: Python :: 3.11
Classifier: Programming Language :: Python :: 3.12
Classifier: Topic :: Communications
Classifier: Topic :: Software Development
Requires-Dist: anyio (>3,<5)
Project-URL: Repository, https://github.com/rafalkrupinski/ratelimit-anyio.git
